machc/configurator/__init__.py
machc/configurator/configurator.py
machc/configurator/file_configurator.py
machc/configurator/properties_configurator.py
machc/configurator/yaml_configurator.py
machc_configurator-0.0.2.dist-info/METADATA
machc_configurator-0.0.2.dist-info/WHEEL
machc_configurator-0.0.2.dist-info/top_level.txt
machc_configurator-0.0.2.dist-info/RECORD
