Metadata-Version: 2.4
Name: machc.configurator
Version: 0.0.2
Summary: Offers flexible configuration management for various ways of configuration provisioning.
Author-email: Viktor Tovstyi <viktor.tovstyi@gmail.com>
Requires-Python: ==3.12.3
Requires-Dist: utils==1.0.2
Requires-Dist: PyYAML==6.0.2
